[{"host":{"consumption":872063.0,"timestamp":1696347305.4627504},"consumers":[{"exe":"scaphandre","pid":258023,"consumption":581375.0,"timestamp":1696347305.485146,"container":null},{"exe":"amf","pid":257872,"consumption":436031.0,"timestamp":1696347305.4848123,"container":null},{"exe":"systemd","pid":1,"consumption":0.0,"timestamp":1696347305.4763334,"container":null},{"exe":"kthreadd","pid":2,"consumption":0.0,"timestamp":1696347305.4763558,"container":null},{"exe":"rcu_gp","pid":3,"consumption":0.0,"timestamp":1696347305.4763758,"container":null},{"exe":"rcu_par_gp","pid":4,"consumption":0.0,"timestamp":1696347305.4763947,"container":null},{"exe":"slub_flushwq","pid":5,"consumption":0.0,"timestamp":1696347305.47642,"container":null},{"exe":"netns","pid":6,"consumption":0.0,"timestamp":1696347305.4764433,"container":null},{"exe":"kworker/0:0H-events_highpri","pid":8,"consumption":0.0,"timestamp":1696347305.4764676,"container":null},{"exe":"mm_percpu_wq","pid":10,"consumption":0.0,"timestamp":1696347305.4764915,"container":null}],"sockets":[]},{"host":{"consumption":1077511.0,"timestamp":1696347306.5091424},"consumers":[{"exe":"scaphandre","pid":258023,"consumption":1077511.0,"timestamp":1696347306.533275,"container":null},{"exe":"ksoftirqd/3","pid":34,"consumption":215502.0,"timestamp":1696347306.524895,"container":null},{"exe":"mongod","pid":720,"consumption":215502.0,"timestamp":1696347306.5267873,"container":null},{"exe":"amf","pid":257872,"consumption":215502.0,"timestamp":1696347306.5328903,"container":null},{"exe":"systemd","pid":1,"consumption":0.0,"timestamp":1696347306.5242796,"container":null},{"exe":"kthreadd","pid":2,"consumption":0.0,"timestamp":1696347306.5243056,"container":null},{"exe":"rcu_gp","pid":3,"consumption":0.0,"timestamp":1696347306.5243287,"container":null},{"exe":"rcu_par_gp","pid":4,"consumption":0.0,"timestamp":1696347306.5243514,"container":null},{"exe":"slub_flushwq","pid":5,"consumption":0.0,"timestamp":1696347306.5243735,"container":null},{"exe":"netns","pid":6,"consumption":0.0,"timestamp":1696347306.5243952,"container":null}],"sockets":[]},{"host":{"consumption":892821.0,"timestamp":1696347307.5597968},"consumers":[{"exe":"scaphandre","pid":258023,"consumption":744017.0,"timestamp":1696347307.58466,"container":null},{"exe":"mongod","pid":720,"consumption":148803.0,"timestamp":1696347307.5788462,"container":null},{"exe":"python3","pid":258003,"consumption":148803.0,"timestamp":1696347307.5846157,"container":null},{"exe":"systemd","pid":1,"consumption":0.0,"timestamp":1696347307.575432,"container":null},{"exe":"kthreadd","pid":2,"consumption":0.0,"timestamp":1696347307.5754576,"container":null},{"exe":"rcu_gp","pid":3,"consumption":0.0,"timestamp":1696347307.5754805,"container":null},{"exe":"rcu_par_gp","pid":4,"consumption":0.0,"timestamp":1696347307.5755029,"container":null},{"exe":"slub_flushwq","pid":5,"consumption":0.0,"timestamp":1696347307.5755253,"container":null},{"exe":"netns","pid":6,"consumption":0.0,"timestamp":1696347307.5755472,"container":null},{"exe":"kworker/0:0H-events_highpri","pid":8,"consumption":0.0,"timestamp":1696347307.5755699,"container":null}],"sockets":[]},{"host":{"consumption":1062110.0,"timestamp":1696347308.6083746},"consumers":[{"exe":"scaphandre","pid":258023,"consumption":885091.0,"timestamp":1696347308.6372871,"container":null},{"exe":"python3","pid":258003,"consumption":177018.0,"timestamp":1696347308.6372435,"container":null},{"exe":"systemd","pid":1,"consumption":0.0,"timestamp":1696347308.625206,"container":null},{"exe":"kthreadd","pid":2,"consumption":0.0,"timestamp":1696347308.6252394,"container":null},{"exe":"rcu_gp","pid":3,"consumption":0.0,"timestamp":1696347308.6252677,"container":null},{"exe":"rcu_par_gp","pid":4,"consumption":0.0,"timestamp":1696347308.6252959,"container":null},{"exe":"slub_flushwq","pid":5,"consumption":0.0,"timestamp":1696347308.6253238,"container":null},{"exe":"netns","pid":6,"consumption":0.0,"timestamp":1696347308.6253517,"container":null},{"exe":"kworker/0:0H-events_highpri","pid":8,"consumption":0.0,"timestamp":1696347308.6253788,"container":null},{"exe":"mm_percpu_wq","pid":10,"consumption":0.0,"timestamp":1696347308.6254058,"container":null}],"sockets":[]},{"host":{"consumption":895065.0,"timestamp":1696347309.661645},"consumers":[{"exe":"scaphandre","pid":258023,"consumption":639332.0,"timestamp":1696347309.6876004,"container":null},{"exe":"systemd","pid":1,"consumption":127866.0,"timestamp":1696347309.6783433,"container":null},{"exe":"ksoftirqd/3","pid":34,"consumption":127866.0,"timestamp":1696347309.6789773,"container":null},{"exe":"mongod","pid":720,"consumption":127866.0,"timestamp":1696347309.6809368,"container":null},{"exe":"kthreadd","pid":2,"consumption":0.0,"timestamp":1696347309.678371,"container":null},{"exe":"rcu_gp","pid":3,"consumption":0.0,"timestamp":1696347309.6783946,"container":null},{"exe":"rcu_par_gp","pid":4,"consumption":0.0,"timestamp":1696347309.6784174,"container":null},{"exe":"slub_flushwq","pid":5,"consumption":0.0,"timestamp":1696347309.67844,"container":null},{"exe":"netns","pid":6,"consumption":0.0,"timestamp":1696347309.678464,"container":null},{"exe":"kworker/0:0H-events_highpri","pid":8,"consumption":0.0,"timestamp":1696347309.678487,"container":null}],"sockets":[]},{"host":{"consumption":1117484.0,"timestamp":1696347310.7131002},"consumers":[{"exe":"scaphandre","pid":258023,"consumption":698427.0,"timestamp":1696347310.740584,"container":null},{"exe":"gnome-shell","pid":220520,"consumption":279371.0,"timestamp":1696347310.7375247,"container":null},{"exe":"mongod","pid":720,"consumption":139685.0,"timestamp":1696347310.733108,"container":null},{"exe":"systemd","pid":1,"consumption":0.0,"timestamp":1696347310.7301893,"container":null},{"exe":"kthreadd","pid":2,"consumption":0.0,"timestamp":1696347310.7302213,"container":null},{"exe":"rcu_gp","pid":3,"consumption":0.0,"timestamp":1696347310.7302477,"container":null},{"exe":"rcu_par_gp","pid":4,"consumption":0.0,"timestamp":1696347310.730273,"container":null},{"exe":"slub_flushwq","pid":5,"consumption":0.0,"timestamp":1696347310.7302983,"container":null},{"exe":"netns","pid":6,"consumption":0.0,"timestamp":1696347310.7303233,"container":null},{"exe":"kworker/0:0H-events_highpri","pid":8,"consumption":0.0,"timestamp":1696347310.7303483,"container":null}],"sockets":[]},{"host":{"consumption":851872.0,"timestamp":1696347311.764894},"consumers":[{"exe":"scaphandre","pid":258023,"consumption":851872.0,"timestamp":1696347311.7907243,"container":null},{"exe":"ksoftirqd/3","pid":34,"consumption":170374.0,"timestamp":1696347311.7829354,"container":null},{"exe":"udr","pid":257893,"consumption":170374.0,"timestamp":1696347311.7904253,"container":null},{"exe":"python3","pid":258003,"consumption":170374.0,"timestamp":1696347311.79068,"container":null},{"exe":"systemd","pid":1,"consumption":0.0,"timestamp":1696347311.7810345,"container":null},{"exe":"kthreadd","pid":2,"consumption":0.0,"timestamp":1696347311.781062,"container":null},{"exe":"rcu_gp","pid":3,"consumption":0.0,"timestamp":1696347311.7810845,"container":null},{"exe":"rcu_par_gp","pid":4,"consumption":0.0,"timestamp":1696347311.7811072,"container":null},{"exe":"slub_flushwq","pid":5,"consumption":0.0,"timestamp":1696347311.7811296,"container":null},{"exe":"netns","pid":6,"consumption":0.0,"timestamp":1696347311.7811525,"container":null}],"sockets":[]},{"host":{"consumption":1042588.0,"timestamp":1696347312.8139038},"consumers":[{"exe":"scaphandre","pid":258023,"consumption":1042588.0,"timestamp":1696347312.842611,"container":null},{"exe":"gvfs-afc-volume","pid":1443,"consumption":208517.0,"timestamp":1696347312.8379912,"container":null},{"exe":"systemd","pid":1,"consumption":0.0,"timestamp":1696347312.8324974,"container":null},{"exe":"kthreadd","pid":2,"consumption":0.0,"timestamp":1696347312.8325284,"container":null},{"exe":"rcu_gp","pid":3,"consumption":0.0,"timestamp":1696347312.8325546,"container":null},{"exe":"rcu_par_gp","pid":4,"consumption":0.0,"timestamp":1696347312.8325796,"container":null},{"exe":"slub_flushwq","pid":5,"consumption":0.0,"timestamp":1696347312.8326044,"container":null},{"exe":"netns","pid":6,"consumption":0.0,"timestamp":1696347312.8326292,"container":null},{"exe":"kworker/0:0H-events_highpri","pid":8,"consumption":0.0,"timestamp":1696347312.8326545,"container":null},{"exe":"mm_percpu_wq","pid":10,"consumption":0.0,"timestamp":1696347312.8326793,"container":null}],"sockets":[]},{"host":{"consumption":786247.0,"timestamp":1696347313.8653777},"consumers":[{"exe":"scaphandre","pid":258023,"consumption":1179370.0,"timestamp":1696347313.8923647,"container":null},{"exe":"mongod","pid":720,"consumption":196561.0,"timestamp":1696347313.8851495,"container":null},{"exe":"systemd","pid":1,"consumption":0.0,"timestamp":1696347313.8825774,"container":null},{"exe":"kthreadd","pid":2,"consumption":0.0,"timestamp":1696347313.8826048,"container":null},{"exe":"rcu_gp","pid":3,"consumption":0.0,"timestamp":1696347313.8826287,"container":null},{"exe":"rcu_par_gp","pid":4,"consumption":0.0,"timestamp":1696347313.8826525,"container":null},{"exe":"slub_flushwq","pid":5,"consumption":0.0,"timestamp":1696347313.8826754,"container":null},{"exe":"netns","pid":6,"consumption":0.0,"timestamp":1696347313.8826978,"container":null},{"exe":"kworker/0:0H-events_highpri","pid":8,"consumption":0.0,"timestamp":1696347313.8827205,"container":null},{"exe":"mm_percpu_wq","pid":10,"consumption":0.0,"timestamp":1696347313.882743,"container":null}],"sockets":[]},{"host":{"consumption":1066342.0,"timestamp":1696347314.9178653},"consumers":[{"exe":"scaphandre","pid":258023,"consumption":853073.0,"timestamp":1696347314.944737,"container":null},{"exe":"ksoftirqd/3","pid":34,"consumption":213268.0,"timestamp":1696347314.9355226,"container":null},{"exe":"systemd","pid":1,"consumption":0.0,"timestamp":1696347314.9348948,"container":null},{"exe":"kthreadd","pid":2,"consumption":0.0,"timestamp":1696347314.9349227,"container":null},{"exe":"rcu_gp","pid":3,"consumption":0.0,"timestamp":1696347314.934946,"container":null},{"exe":"rcu_par_gp","pid":4,"consumption":0.0,"timestamp":1696347314.9349685,"container":null},{"exe":"slub_flushwq","pid":5,"consumption":0.0,"timestamp":1696347314.9349906,"container":null},{"exe":"netns","pid":6,"consumption":0.0,"timestamp":1696347314.935013,"container":null},{"exe":"kworker/0:0H-events_highpri","pid":8,"consumption":0.0,"timestamp":1696347314.935036,"container":null},{"exe":"mm_percpu_wq","pid":10,"consumption":0.0,"timestamp":1696347314.9350588,"container":null}],"sockets":[]},{"host":{"consumption":785587.0,"timestamp":1696347315.968203},"consumers":[{"exe":"scaphandre","pid":258023,"consumption":785587.0,"timestamp":1696347315.9931152,"container":null},{"exe":"pcf","pid":257904,"consumption":157117.0,"timestamp":1696347315.992859,"container":null},{"exe":"python3","pid":258003,"consumption":157117.0,"timestamp":1696347315.99307,"container":null},{"exe":"systemd","pid":1,"consumption":0.0,"timestamp":1696347315.983558,"container":null},{"exe":"kthreadd","pid":2,"consumption":0.0,"timestamp":1696347315.9835854,"container":null},{"exe":"rcu_gp","pid":3,"consumption":0.0,"timestamp":1696347315.983608,"container":null},{"exe":"rcu_par_gp","pid":4,"consumption":0.0,"timestamp":1696347315.98363,"container":null},{"exe":"slub_flushwq","pid":5,"consumption":0.0,"timestamp":1696347315.983652,"container":null},{"exe":"netns","pid":6,"consumption":0.0,"timestamp":1696347315.9836748,"container":null},{"exe":"kworker/0:0H-events_highpri","pid":8,"consumption":0.0,"timestamp":1696347315.9836974,"container":null}],"sockets":[]},{"host":{"consumption":1052515.0,"timestamp":1696347317.0167139},"consumers":[{"exe":"scaphandre","pid":258023,"consumption":701676.0,"timestamp":1696347317.0417914,"container":null},{"exe":"mongod","pid":720,"consumption":175419.0,"timestamp":1696347317.0348167,"container":null},{"exe":"systemd","pid":1,"consumption":0.0,"timestamp":1696347317.032253,"container":null},{"exe":"kthreadd","pid":2,"consumption":0.0,"timestamp":1696347317.0322814,"container":null},{"exe":"rcu_gp","pid":3,"consumption":0.0,"timestamp":1696347317.0323048,"container":null},{"exe":"rcu_par_gp","pid":4,"consumption":0.0,"timestamp":1696347317.0323277,"container":null},{"exe":"slub_flushwq","pid":5,"consumption":0.0,"timestamp":1696347317.0323498,"container":null},{"exe":"netns","pid":6,"consumption":0.0,"timestamp":1696347317.032372,"container":null},{"exe":"kworker/0:0H-events_highpri","pid":8,"consumption":0.0,"timestamp":1696347317.0323942,"container":null},{"exe":"mm_percpu_wq","pid":10,"consumption":0.0,"timestamp":1696347317.032417,"container":null}],"sockets":[]},{"host":{"consumption":1049306.0,"timestamp":1696347318.0662785},"consumers":[{"exe":"scaphandre","pid":258023,"consumption":1049306.0,"timestamp":1696347318.09435,"container":null},{"exe":"ksoftirqd/3","pid":34,"consumption":149900.0,"timestamp":1696347318.088019,"container":null},{"exe":"thermald","pid":633,"consumption":149900.0,"timestamp":1696347318.0897958,"container":null},{"exe":"mongod","pid":720,"consumption":149900.0,"timestamp":1696347318.0899608,"container":null},{"exe":"pcf","pid":257904,"consumption":149900.0,"timestamp":1696347318.094156,"container":null},{"exe":"systemd","pid":1,"consumption":0.0,"timestamp":1696347318.0872645,"container":null},{"exe":"kthreadd","pid":2,"consumption":0.0,"timestamp":1696347318.0872967,"container":null},{"exe":"rcu_gp","pid":3,"consumption":0.0,"timestamp":1696347318.0873232,"container":null},{"exe":"rcu_par_gp","pid":4,"consumption":0.0,"timestamp":1696347318.087349,"container":null},{"exe":"slub_flushwq","pid":5,"consumption":0.0,"timestamp":1696347318.0873742,"container":null}],"sockets":[]},{"host":{"consumption":1040044.0,"timestamp":1696347319.115332},"consumers":[{"exe":"scaphandre","pid":258023,"consumption":693362.0,"timestamp":1696347319.1467946,"container":null},{"exe":"python3","pid":258003,"consumption":173340.0,"timestamp":1696347319.1467586,"container":null},{"exe":"systemd","pid":1,"consumption":0.0,"timestamp":1696347319.1362753,"container":null},{"exe":"kthreadd","pid":2,"consumption":0.0,"timestamp":1696347319.1363115,"container":null},{"exe":"rcu_gp","pid":3,"consumption":0.0,"timestamp":1696347319.1363428,"container":null},{"exe":"rcu_par_gp","pid":4,"consumption":0.0,"timestamp":1696347319.1363728,"container":null},{"exe":"slub_flushwq","pid":5,"consumption":0.0,"timestamp":1696347319.136403,"container":null},{"exe":"netns","pid":6,"consumption":0.0,"timestamp":1696347319.136432,"container":null},{"exe":"kworker/0:0H-events_highpri","pid":8,"consumption":0.0,"timestamp":1696347319.136461,"container":null},{"exe":"mm_percpu_wq","pid":10,"consumption":0.0,"timestamp":1696347319.1364894,"container":null}],"sockets":[]},{"host":{"consumption":1043543.0,"timestamp":1696347320.1693487},"consumers":[{"exe":"scaphandre","pid":258023,"consumption":1043543.0,"timestamp":1696347320.2031515,"container":null},{"exe":"mongod","pid":720,"consumption":417417.0,"timestamp":1696347320.1966126,"container":null},{"exe":"rcu_sched","pid":14,"consumption":208708.0,"timestamp":1696347320.1935396,"container":null},{"exe":"ksoftirqd/3","pid":34,"consumption":208708.0,"timestamp":1696347320.194092,"container":null},{"exe":"systemd","pid":1,"consumption":0.0,"timestamp":1696347320.1931362,"container":null},{"exe":"kthreadd","pid":2,"consumption":0.0,"timestamp":1696347320.193194,"container":null},{"exe":"rcu_gp","pid":3,"consumption":0.0,"timestamp":1696347320.193225,"container":null},{"exe":"rcu_par_gp","pid":4,"consumption":0.0,"timestamp":1696347320.193254,"container":null},{"exe":"slub_flushwq","pid":5,"consumption":0.0,"timestamp":1696347320.1932828,"container":null},{"exe":"netns","pid":6,"consumption":0.0,"timestamp":1696347320.1933115,"container":null}],"sockets":[]},{"host":{"consumption":978031.0,"timestamp":1696347321.2248206},"consumers":[{"exe":"scaphandre","pid":258023,"consumption":838312.0,"timestamp":1696347321.2552886,"container":null},{"exe":"ksoftirqd/3","pid":34,"consumption":139718.0,"timestamp":1696347321.2472336,"container":null},{"exe":"gsd-housekeepin","pid":220645,"consumption":139718.0,"timestamp":1696347321.2539227,"container":null},{"exe":"python3","pid":258003,"consumption":139718.0,"timestamp":1696347321.2552612,"container":null},{"exe":"systemd","pid":1,"consumption":0.0,"timestamp":1696347321.2464287,"container":null},{"exe":"kthreadd","pid":2,"consumption":0.0,"timestamp":1696347321.2464643,"container":null},{"exe":"rcu_gp","pid":3,"consumption":0.0,"timestamp":1696347321.2464938,"container":null},{"exe":"rcu_par_gp","pid":4,"consumption":0.0,"timestamp":1696347321.2465224,"container":null},{"exe":"slub_flushwq","pid":5,"consumption":0.0,"timestamp":1696347321.2465508,"container":null},{"exe":"netns","pid":6,"consumption":0.0,"timestamp":1696347321.2465808,"container":null}],"sockets":[]},{"host":{"consumption":1046262.0,"timestamp":1696347322.2767978},"consumers":[{"exe":"scaphandre","pid":258023,"consumption":1046262.0,"timestamp":1696347322.3093724,"container":null},{"exe":"mongod","pid":720,"consumption":174377.0,"timestamp":1696347322.3045354,"container":null},{"exe":"systemd","pid":1,"consumption":0.0,"timestamp":1696347322.3012848,"container":null},{"exe":"kthreadd","pid":2,"consumption":0.0,"timestamp":1696347322.301321,"container":null},{"exe":"rcu_gp","pid":3,"consumption":0.0,"timestamp":1696347322.3013525,"container":null},{"exe":"rcu_par_gp","pid":4,"consumption":0.0,"timestamp":1696347322.301382,"container":null},{"exe":"slub_flushwq","pid":5,"consumption":0.0,"timestamp":1696347322.3014112,"container":null},{"exe":"netns","pid":6,"consumption":0.0,"timestamp":1696347322.3014398,"container":null},{"exe":"kworker/0:0H-events_highpri","pid":8,"consumption":0.0,"timestamp":1696347322.3014686,"container":null},{"exe":"mm_percpu_wq","pid":10,"consumption":0.0,"timestamp":1696347322.3014977,"container":null}],"sockets":[]},{"host":{"consumption":1007682.0,"timestamp":1696347323.330771},"consumers":[{"exe":"scaphandre","pid":258023,"consumption":503841.0,"timestamp":1696347323.3610654,"container":null},{"exe":"amf","pid":257872,"consumption":377880.0,"timestamp":1696347323.3608048,"container":null},{"exe":"ksoftirqd/3","pid":34,"consumption":125960.0,"timestamp":1696347323.3535533,"container":null},{"exe":"python3","pid":258003,"consumption":125960.0,"timestamp":1696347323.361038,"container":null},{"exe":"systemd","pid":1,"consumption":0.0,"timestamp":1696347323.3527439,"container":null},{"exe":"kthreadd","pid":2,"consumption":0.0,"timestamp":1696347323.3527792,"container":null},{"exe":"rcu_gp","pid":3,"consumption":0.0,"timestamp":1696347323.3528082,"container":null},{"exe":"rcu_par_gp","pid":4,"consumption":0.0,"timestamp":1696347323.352837,"container":null},{"exe":"slub_flushwq","pid":5,"consumption":0.0,"timestamp":1696347323.3528662,"container":null},{"exe":"netns","pid":6,"consumption":0.0,"timestamp":1696347323.3528953,"container":null}],"sockets":[]},{"host":{"consumption":1099607.0,"timestamp":1696347324.3822796},"consumers":[{"exe":"scaphandre","pid":258023,"consumption":610892.0,"timestamp":1696347324.4136996,"container":null},{"exe":"amf","pid":257872,"consumption":366535.0,"timestamp":1696347324.4133832,"container":null},{"exe":"ksoftirqd/3","pid":34,"consumption":122178.0,"timestamp":1696347324.4047823,"container":null},{"exe":"systemd","pid":1,"consumption":0.0,"timestamp":1696347324.4039764,"container":null},{"exe":"kthreadd","pid":2,"consumption":0.0,"timestamp":1696347324.4040112,"container":null},{"exe":"rcu_gp","pid":3,"consumption":0.0,"timestamp":1696347324.4040415,"container":null},{"exe":"rcu_par_gp","pid":4,"consumption":0.0,"timestamp":1696347324.4040716,"container":null},{"exe":"slub_flushwq","pid":5,"consumption":0.0,"timestamp":1696347324.4040997,"container":null},{"exe":"netns","pid":6,"consumption":0.0,"timestamp":1696347324.4041286,"container":null},{"exe":"kworker/0:0H-events_highpri","pid":8,"consumption":0.0,"timestamp":1696347324.4041576,"container":null}],"sockets":[]},{"host":{"consumption":921392.0,"timestamp":1696347325.4362586},"consumers":[{"exe":"scaphandre","pid":258023,"consumption":2303480.0,"timestamp":1696347325.4464712,"container":null},{"exe":"mongod","pid":720,"consumption":921392.0,"timestamp":1696347325.4446354,"container":null},{"exe":"systemd","pid":1,"consumption":0.0,"timestamp":1696347325.4438412,"container":null},{"exe":"kthreadd","pid":2,"consumption":0.0,"timestamp":1696347325.4438493,"container":null},{"exe":"rcu_gp","pid":3,"consumption":0.0,"timestamp":1696347325.4438562,"container":null},{"exe":"rcu_par_gp","pid":4,"consumption":0.0,"timestamp":1696347325.443863,"container":null},{"exe":"slub_flushwq","pid":5,"consumption":0.0,"timestamp":1696347325.4438696,"container":null},{"exe":"netns","pid":6,"consumption":0.0,"timestamp":1696347325.4438763,"container":null},{"exe":"kworker/0:0H-events_highpri","pid":8,"consumption":0.0,"timestamp":1696347325.443888,"container":null},{"exe":"mm_percpu_wq","pid":10,"consumption":0.0,"timestamp":1696347325.4438949,"container":null}],"sockets":[]},{"host":{"consumption":1093433.0,"timestamp":1696347326.4594872},"consumers":[{"exe":"scaphandre","pid":258023,"consumption":728955.0,"timestamp":1696347326.4703035,"container":null},{"exe":"ksoftirqd/3","pid":34,"consumption":364477.0,"timestamp":1696347326.4678977,"container":null},{"exe":"systemd","pid":1,"consumption":0.0,"timestamp":1696347326.4677064,"container":null},{"exe":"kthreadd","pid":2,"consumption":0.0,"timestamp":1696347326.4677143,"container":null},{"exe":"rcu_gp","pid":3,"consumption":0.0,"timestamp":1696347326.4677212,"container":null},{"exe":"rcu_par_gp","pid":4,"consumption":0.0,"timestamp":1696347326.4677286,"container":null},{"exe":"slub_flushwq","pid":5,"consumption":0.0,"timestamp":1696347326.467735,"container":null},{"exe":"netns","pid":6,"consumption":0.0,"timestamp":1696347326.4677417,"container":null},{"exe":"kworker/0:0H-events_highpri","pid":8,"consumption":0.0,"timestamp":1696347326.4677486,"container":null},{"exe":"mm_percpu_wq","pid":10,"consumption":0.0,"timestamp":1696347326.467755,"container":null}],"sockets":[]},{"host":{"consumption":963296.0,"timestamp":1696347327.4835846},"consumers":[{"exe":"nrf","pid":257860,"consumption":642197.0,"timestamp":1696347327.4934514,"container":null},{"exe":"scaphandre","pid":258023,"consumption":642197.0,"timestamp":1696347327.4935842,"container":null},{"exe":"python3","pid":258003,"consumption":321098.0,"timestamp":1696347327.4935706,"container":null},{"exe":"systemd","pid":1,"consumption":0.0,"timestamp":1696347327.4909503,"container":null},{"exe":"kthreadd","pid":2,"consumption":0.0,"timestamp":1696347327.4909592,"container":null},{"exe":"rcu_gp","pid":3,"consumption":0.0,"timestamp":1696347327.4909668,"container":null},{"exe":"rcu_par_gp","pid":4,"consumption":0.0,"timestamp":1696347327.490974,"container":null},{"exe":"slub_flushwq","pid":5,"consumption":0.0,"timestamp":1696347327.490981,"container":null},{"exe":"netns","pid":6,"consumption":0.0,"timestamp":1696347327.4909878,"container":null},{"exe":"kworker/0:0H-events_highpri","pid":8,"consumption":0.0,"timestamp":1696347327.4909947,"container":null}],"sockets":[]},{"host":{"consumption":1102684.0,"timestamp":1696347328.5065875},"consumers":[{"exe":"scaphandre","pid":258023,"consumption":735122.0,"timestamp":1696347328.5173783,"container":null},{"exe":"ksoftirqd/3","pid":34,"consumption":367561.0,"timestamp":1696347328.5149434,"container":null},{"exe":"mongod","pid":720,"consumption":367561.0,"timestamp":1696347328.5155396,"container":null},{"exe":"systemd","pid":1,"consumption":0.0,"timestamp":1696347328.5147529,"container":null},{"exe":"kthreadd","pid":2,"consumption":0.0,"timestamp":1696347328.5147612,"container":null},{"exe":"rcu_gp","pid":3,"consumption":0.0,"timestamp":1696347328.5147681,"container":null},{"exe":"rcu_par_gp","pid":4,"consumption":0.0,"timestamp":1696347328.514775,"container":null},{"exe":"slub_flushwq","pid":5,"consumption":0.0,"timestamp":1696347328.5147817,"container":null},{"exe":"netns","pid":6,"consumption":0.0,"timestamp":1696347328.5147882,"container":null},{"exe":"kworker/0:0H-events_highpri","pid":8,"consumption":0.0,"timestamp":1696347328.5147953,"container":null}],"sockets":[]},{"host":{"consumption":955772.0,"timestamp":1696347329.5305076},"consumers":[{"exe":"scaphandre","pid":258023,"consumption":477886.0,"timestamp":1696347329.540969,"container":null},{"exe":"migration/3","pid":33,"consumption":238943.0,"timestamp":1696347329.5385547,"container":null},{"exe":"systemd-resolve","pid":557,"consumption":238943.0,"timestamp":1696347329.5389137,"container":null},{"exe":"mongod","pid":720,"consumption":238943.0,"timestamp":1696347329.5391595,"container":null},{"exe":"systemd","pid":1,"consumption":0.0,"timestamp":1696347329.5383725,"container":null},{"exe":"kthreadd","pid":2,"consumption":0.0,"timestamp":1696347329.5383804,"container":null},{"exe":"rcu_gp","pid":3,"consumption":0.0,"timestamp":1696347329.5383875,"container":null},{"exe":"rcu_par_gp","pid":4,"consumption":0.0,"timestamp":1696347329.538395,"container":null},{"exe":"slub_flushwq","pid":5,"consumption":0.0,"timestamp":1696347329.5384016,"container":null},{"exe":"netns","pid":6,"consumption":0.0,"timestamp":1696347329.538408,"container":null}],"sockets":[]},{"host":{"consumption":1126602.0,"timestamp":1696347330.5539489},"consumers":[{"exe":"scaphandre","pid":258023,"consumption":844951.0,"timestamp":1696347330.5648003,"container":null},{"exe":"mongod","pid":720,"consumption":281650.0,"timestamp":1696347330.5629232,"container":null},{"exe":"systemd","pid":1,"consumption":0.0,"timestamp":1696347330.5621006,"container":null},{"exe":"kthreadd","pid":2,"consumption":0.0,"timestamp":1696347330.5621092,"container":null},{"exe":"rcu_gp","pid":3,"consumption":0.0,"timestamp":1696347330.5621166,"container":null},{"exe":"rcu_par_gp","pid":4,"consumption":0.0,"timestamp":1696347330.5621235,"container":null},{"exe":"slub_flushwq","pid":5,"consumption":0.0,"timestamp":1696347330.5621305,"container":null},{"exe":"netns","pid":6,"consumption":0.0,"timestamp":1696347330.5621371,"container":null},{"exe":"kworker/0:0H-events_highpri","pid":8,"consumption":0.0,"timestamp":1696347330.562144,"container":null},{"exe":"mm_percpu_wq","pid":10,"consumption":0.0,"timestamp":1696347330.5621507,"container":null}],"sockets":[]},{"host":{"consumption":977671.0,"timestamp":1696347331.5779703},"consumers":[{"exe":"scaphandre","pid":258023,"consumption":651780.0,"timestamp":1696347331.5887468,"container":null},{"exe":"ksoftirqd/3","pid":34,"consumption":325890.0,"timestamp":1696347331.5863893,"container":null},{"exe":"python3","pid":258003,"consumption":325890.0,"timestamp":1696347331.5887334,"container":null},{"exe":"systemd","pid":1,"consumption":0.0,"timestamp":1696347331.5862014,"container":null},{"exe":"kthreadd","pid":2,"consumption":0.0,"timestamp":1696347331.5862103,"container":null},{"exe":"rcu_gp","pid":3,"consumption":0.0,"timestamp":1696347331.5862176,"container":null},{"exe":"rcu_par_gp","pid":4,"consumption":0.0,"timestamp":1696347331.5862246,"container":null},{"exe":"slub_flushwq","pid":5,"consumption":0.0,"timestamp":1696347331.5862315,"container":null},{"exe":"netns","pid":6,"consumption":0.0,"timestamp":1696347331.5862377,"container":null},{"exe":"kworker/0:0H-events_highpri","pid":8,"consumption":0.0,"timestamp":1696347331.5862443,"container":null}],"sockets":[]},{"host":{"consumption":1130105.0,"timestamp":1696347332.601589},"consumers":[{"exe":"scaphandre","pid":258023,"consumption":753403.0,"timestamp":1696347332.6120524,"container":null},{"exe":"mongod","pid":720,"consumption":376701.0,"timestamp":1696347332.6102366,"container":null},{"exe":"systemd","pid":1,"consumption":0.0,"timestamp":1696347332.6094506,"container":null},{"exe":"kthreadd","pid":2,"consumption":0.0,"timestamp":1696347332.6094594,"container":null},{"exe":"rcu_gp","pid":3,"consumption":0.0,"timestamp":1696347332.6094663,"container":null},{"exe":"rcu_par_gp","pid":4,"consumption":0.0,"timestamp":1696347332.6094732,"container":null},{"exe":"slub_flushwq","pid":5,"consumption":0.0,"timestamp":1696347332.6094806,"container":null},{"exe":"netns","pid":6,"consumption":0.0,"timestamp":1696347332.6094873,"container":null},{"exe":"kworker/0:0H-events_highpri","pid":8,"consumption":0.0,"timestamp":1696347332.6094944,"container":null},{"exe":"mm_percpu_wq","pid":10,"consumption":0.0,"timestamp":1696347332.609501,"container":null}],"sockets":[]},{"host":{"consumption":912108.0,"timestamp":1696347333.6250741},"consumers":[{"exe":"scaphandre","pid":258023,"consumption":1368162.0,"timestamp":1696347333.6351979,"container":null},{"exe":"ksoftirqd/3","pid":34,"consumption":456054.0,"timestamp":1696347333.6327891,"container":null},{"exe":"accounts-daemon","pid":591,"consumption":456054.0,"timestamp":1696347333.6331613,"container":null},{"exe":"amf","pid":257872,"consumption":456054.0,"timestamp":1696347333.635082,"container":null},{"exe":"systemd","pid":1,"consumption":0.0,"timestamp":1696347333.6325996,"container":null},{"exe":"kthreadd","pid":2,"consumption":0.0,"timestamp":1696347333.6326084,"container":null},{"exe":"rcu_gp","pid":3,"consumption":0.0,"timestamp":1696347333.6326156,"container":null},{"exe":"rcu_par_gp","pid":4,"consumption":0.0,"timestamp":1696347333.6326222,"container":null},{"exe":"slub_flushwq","pid":5,"consumption":0.0,"timestamp":1696347333.6326292,"container":null},{"exe":"netns","pid":6,"consumption":0.0,"timestamp":1696347333.6326356,"container":null}],"sockets":[]}]