[{"host":{"consumption":1357351.0,"timestamp":1696347369.525144},"consumers":[{"exe":"scaphandre","pid":258028,"consumption":1357351.0,"timestamp":1696347369.549767,"container":null},{"exe":"ksoftirqd/3","pid":34,"consumption":271470.0,"timestamp":1696347369.5436013,"container":null},{"exe":"mongod","pid":720,"consumption":271470.0,"timestamp":1696347369.545605,"container":null},{"exe":"snapd","pid":230116,"consumption":271470.0,"timestamp":1696347369.5487018,"container":null},{"exe":"systemd","pid":1,"consumption":0.0,"timestamp":1696347369.5431433,"container":null},{"exe":"kthreadd","pid":2,"consumption":0.0,"timestamp":1696347369.5431626,"container":null},{"exe":"rcu_gp","pid":3,"consumption":0.0,"timestamp":1696347369.5431793,"container":null},{"exe":"rcu_par_gp","pid":4,"consumption":0.0,"timestamp":1696347369.543195,"container":null},{"exe":"slub_flushwq","pid":5,"consumption":0.0,"timestamp":1696347369.5432162,"container":null},{"exe":"netns","pid":6,"consumption":0.0,"timestamp":1696347369.5432363,"container":null}],"sockets":[]},{"host":{"consumption":1631549.0,"timestamp":1696347370.5756326},"consumers":[{"exe":"scaphandre","pid":258028,"consumption":725132.0,"timestamp":1696347370.5987525,"container":null},{"exe":"gnome-shell","pid":220520,"consumption":543849.0,"timestamp":1696347370.5972815,"container":null},{"exe":"pcf","pid":257904,"consumption":181283.0,"timestamp":1696347370.5986152,"container":null},{"exe":"python3","pid":258003,"consumption":181283.0,"timestamp":1696347370.5987287,"container":null},{"exe":"systemd","pid":1,"consumption":0.0,"timestamp":1696347370.5927153,"container":null},{"exe":"kthreadd","pid":2,"consumption":0.0,"timestamp":1696347370.5927331,"container":null},{"exe":"rcu_gp","pid":3,"consumption":0.0,"timestamp":1696347370.59275,"container":null},{"exe":"rcu_par_gp","pid":4,"consumption":0.0,"timestamp":1696347370.5927663,"container":null},{"exe":"slub_flushwq","pid":5,"consumption":0.0,"timestamp":1696347370.5927818,"container":null},{"exe":"netns","pid":6,"consumption":0.0,"timestamp":1696347370.5927978,"container":null}],"sockets":[]},{"host":{"consumption":1400988.0,"timestamp":1696347371.6214695},"consumers":[{"exe":"scaphandre","pid":258028,"consumption":1400988.0,"timestamp":1696347371.6427135,"container":null},{"exe":"ksoftirqd/3","pid":34,"consumption":280197.0,"timestamp":1696347371.6379194,"container":null},{"exe":"amf","pid":257872,"consumption":280197.0,"timestamp":1696347371.6425204,"container":null},{"exe":"systemd","pid":1,"consumption":0.0,"timestamp":1696347371.6375666,"container":null},{"exe":"kthreadd","pid":2,"consumption":0.0,"timestamp":1696347371.6375823,"container":null},{"exe":"rcu_gp","pid":3,"consumption":0.0,"timestamp":1696347371.6375954,"container":null},{"exe":"rcu_par_gp","pid":4,"consumption":0.0,"timestamp":1696347371.637608,"container":null},{"exe":"slub_flushwq","pid":5,"consumption":0.0,"timestamp":1696347371.6376214,"container":null},{"exe":"netns","pid":6,"consumption":0.0,"timestamp":1696347371.6376343,"container":null},{"exe":"kworker/0:0H-events_highpri","pid":8,"consumption":0.0,"timestamp":1696347371.6376476,"container":null}],"sockets":[]},{"host":{"consumption":1541951.0,"timestamp":1696347372.6617892},"consumers":[{"exe":"scaphandre","pid":258028,"consumption":925170.0,"timestamp":1696347372.6830156,"container":null},{"exe":"ksoftirqd/3","pid":34,"consumption":308390.0,"timestamp":1696347372.6753957,"container":null},{"exe":"systemd","pid":1,"consumption":0.0,"timestamp":1696347372.6748862,"container":null},{"exe":"kthreadd","pid":2,"consumption":0.0,"timestamp":1696347372.6749084,"container":null},{"exe":"rcu_gp","pid":3,"consumption":0.0,"timestamp":1696347372.6749282,"container":null},{"exe":"rcu_par_gp","pid":4,"consumption":0.0,"timestamp":1696347372.674947,"container":null},{"exe":"slub_flushwq","pid":5,"consumption":0.0,"timestamp":1696347372.674966,"container":null},{"exe":"netns","pid":6,"consumption":0.0,"timestamp":1696347372.6749845,"container":null},{"exe":"kworker/0:0H-events_highpri","pid":8,"consumption":0.0,"timestamp":1696347372.675004,"container":null},{"exe":"mm_percpu_wq","pid":10,"consumption":0.0,"timestamp":1696347372.6750224,"container":null}],"sockets":[]},{"host":{"consumption":1393074.0,"timestamp":1696347373.7039294},"consumers":[{"exe":"scaphandre","pid":258028,"consumption":1671688.0,"timestamp":1696347373.7262704,"container":null},{"exe":"ksoftirqd/3","pid":34,"consumption":278614.0,"timestamp":1696347373.7212403,"container":null},{"exe":"mongod","pid":720,"consumption":278614.0,"timestamp":1696347373.7226658,"container":null},{"exe":"python3","pid":258003,"consumption":278614.0,"timestamp":1696347373.7262495,"container":null},{"exe":"systemd","pid":1,"consumption":0.0,"timestamp":1696347373.7208033,"container":null},{"exe":"kthreadd","pid":2,"consumption":0.0,"timestamp":1696347373.7208192,"container":null},{"exe":"rcu_gp","pid":3,"consumption":0.0,"timestamp":1696347373.720832,"container":null},{"exe":"rcu_par_gp","pid":4,"consumption":0.0,"timestamp":1696347373.7208452,"container":null},{"exe":"slub_flushwq","pid":5,"consumption":0.0,"timestamp":1696347373.7208583,"container":null},{"exe":"netns","pid":6,"consumption":0.0,"timestamp":1696347373.7208714,"container":null}],"sockets":[]},{"host":{"consumption":1534437.0,"timestamp":1696347374.7508144},"consumers":[{"exe":"scaphandre","pid":258028,"consumption":1022958.0,"timestamp":1696347374.7737975,"container":null},{"exe":"ksoftirqd/3","pid":34,"consumption":255739.0,"timestamp":1696347374.7686327,"container":null},{"exe":"mongod","pid":720,"consumption":255739.0,"timestamp":1696347374.7702117,"container":null},{"exe":"systemd","pid":1,"consumption":0.0,"timestamp":1696347374.7681937,"container":null},{"exe":"kthreadd","pid":2,"consumption":0.0,"timestamp":1696347374.7682135,"container":null},{"exe":"rcu_gp","pid":3,"consumption":0.0,"timestamp":1696347374.7682292,"container":null},{"exe":"rcu_par_gp","pid":4,"consumption":0.0,"timestamp":1696347374.768245,"container":null},{"exe":"slub_flushwq","pid":5,"consumption":0.0,"timestamp":1696347374.7682607,"container":null},{"exe":"netns","pid":6,"consumption":0.0,"timestamp":1696347374.768276,"container":null},{"exe":"kworker/0:0H-events_highpri","pid":8,"consumption":0.0,"timestamp":1696347374.7682917,"container":null}],"sockets":[]},{"host":{"consumption":1402946.0,"timestamp":1696347375.7943652},"consumers":[{"exe":"scaphandre","pid":258028,"consumption":1052209.0,"timestamp":1696347375.804471,"container":null},{"exe":"amf","pid":257872,"consumption":701473.0,"timestamp":1696347375.8043525,"container":null},{"exe":"ksoftirqd/3","pid":34,"consumption":350736.0,"timestamp":1696347375.802059,"container":null},{"exe":"systemd","pid":1,"consumption":0.0,"timestamp":1696347375.8018699,"container":null},{"exe":"kthreadd","pid":2,"consumption":0.0,"timestamp":1696347375.801879,"container":null},{"exe":"rcu_gp","pid":3,"consumption":0.0,"timestamp":1696347375.801886,"container":null},{"exe":"rcu_par_gp","pid":4,"consumption":0.0,"timestamp":1696347375.8018928,"container":null},{"exe":"slub_flushwq","pid":5,"consumption":0.0,"timestamp":1696347375.8019001,"container":null},{"exe":"netns","pid":6,"consumption":0.0,"timestamp":1696347375.8019073,"container":null},{"exe":"kworker/0:0H-events_highpri","pid":8,"consumption":0.0,"timestamp":1696347375.801914,"container":null}],"sockets":[]},{"host":{"consumption":1600820.0,"timestamp":1696347376.8178556},"consumers":[{"exe":"scaphandre","pid":258028,"consumption":1200615.0,"timestamp":1696347376.828052,"container":null},{"exe":"ksoftirqd/3","pid":34,"consumption":800410.0,"timestamp":1696347376.8256214,"container":null},{"exe":"amf","pid":257872,"consumption":800410.0,"timestamp":1696347376.827934,"container":null},{"exe":"mongod","pid":720,"consumption":400205.0,"timestamp":1696347376.8262112,"container":null},{"exe":"systemd","pid":1,"consumption":0.0,"timestamp":1696347376.825418,"container":null},{"exe":"kthreadd","pid":2,"consumption":0.0,"timestamp":1696347376.8254268,"container":null},{"exe":"rcu_gp","pid":3,"consumption":0.0,"timestamp":1696347376.825434,"container":null},{"exe":"rcu_par_gp","pid":4,"consumption":0.0,"timestamp":1696347376.825441,"container":null},{"exe":"slub_flushwq","pid":5,"consumption":0.0,"timestamp":1696347376.8254476,"container":null},{"exe":"netns","pid":6,"consumption":0.0,"timestamp":1696347376.8254547,"container":null}],"sockets":[]},{"host":{"consumption":1390534.0,"timestamp":1696347377.8410501},"consumers":[{"exe":"scaphandre","pid":258028,"consumption":695267.0,"timestamp":1696347377.8509192,"container":null},{"exe":"ksoftirqd/3","pid":34,"consumption":347633.0,"timestamp":1696347377.84856,"container":null},{"exe":"pcf","pid":257904,"consumption":347633.0,"timestamp":1696347377.8508432,"container":null},{"exe":"systemd","pid":1,"consumption":0.0,"timestamp":1696347377.8483734,"container":null},{"exe":"kthreadd","pid":2,"consumption":0.0,"timestamp":1696347377.8483818,"container":null},{"exe":"rcu_gp","pid":3,"consumption":0.0,"timestamp":1696347377.8483887,"container":null},{"exe":"rcu_par_gp","pid":4,"consumption":0.0,"timestamp":1696347377.8483958,"container":null},{"exe":"slub_flushwq","pid":5,"consumption":0.0,"timestamp":1696347377.848402,"container":null},{"exe":"netns","pid":6,"consumption":0.0,"timestamp":1696347377.8484085,"container":null},{"exe":"kworker/0:0H-events_highpri","pid":8,"consumption":0.0,"timestamp":1696347377.8484154,"container":null}],"sockets":[]},{"host":{"consumption":1509600.0,"timestamp":1696347378.8638787},"consumers":[{"exe":"scaphandre","pid":258028,"consumption":1006400.0,"timestamp":1696347378.8740494,"container":null},{"exe":"systemd","pid":1,"consumption":0.0,"timestamp":1696347378.8714151,"container":null},{"exe":"kthreadd","pid":2,"consumption":0.0,"timestamp":1696347378.8714235,"container":null},{"exe":"rcu_gp","pid":3,"consumption":0.0,"timestamp":1696347378.8714302,"container":null},{"exe":"rcu_par_gp","pid":4,"consumption":0.0,"timestamp":1696347378.8714375,"container":null},{"exe":"slub_flushwq","pid":5,"consumption":0.0,"timestamp":1696347378.8714445,"container":null},{"exe":"netns","pid":6,"consumption":0.0,"timestamp":1696347378.8714514,"container":null},{"exe":"kworker/0:0H-events_highpri","pid":8,"consumption":0.0,"timestamp":1696347378.8714602,"container":null},{"exe":"mm_percpu_wq","pid":10,"consumption":0.0,"timestamp":1696347378.8714707,"container":null},{"exe":"rcu_tasks_rude_","pid":11,"consumption":0.0,"timestamp":1696347378.8714821,"container":null}],"sockets":[]},{"host":{"consumption":1367351.0,"timestamp":1696347379.887147},"consumers":[{"exe":"scaphandre","pid":258028,"consumption":820410.0,"timestamp":1696347379.8961027,"container":null},{"exe":"ksoftirqd/3","pid":34,"consumption":273470.0,"timestamp":1696347379.893729,"container":null},{"exe":"mongod","pid":720,"consumption":273470.0,"timestamp":1696347379.8943143,"container":null},{"exe":"python3","pid":258003,"consumption":273470.0,"timestamp":1696347379.896089,"container":null},{"exe":"systemd","pid":1,"consumption":0.0,"timestamp":1696347379.893542,"container":null},{"exe":"kthreadd","pid":2,"consumption":0.0,"timestamp":1696347379.8935506,"container":null},{"exe":"rcu_gp","pid":3,"consumption":0.0,"timestamp":1696347379.8935583,"container":null},{"exe":"rcu_par_gp","pid":4,"consumption":0.0,"timestamp":1696347379.893565,"container":null},{"exe":"slub_flushwq","pid":5,"consumption":0.0,"timestamp":1696347379.8935719,"container":null},{"exe":"netns","pid":6,"consumption":0.0,"timestamp":1696347379.8935785,"container":null}],"sockets":[]},{"host":{"consumption":1537449.0,"timestamp":1696347380.9089158},"consumers":[{"exe":"mongod","pid":720,"consumption":3074898.0,"timestamp":1696347380.9170194,"container":null},{"exe":"udr","pid":257893,"consumption":1537449.0,"timestamp":1696347380.9187148,"container":null},{"exe":"scaphandre","pid":258028,"consumption":1537449.0,"timestamp":1696347380.9188051,"container":null},{"exe":"systemd","pid":1,"consumption":0.0,"timestamp":1696347380.916226,"container":null},{"exe":"kthreadd","pid":2,"consumption":0.0,"timestamp":1696347380.9162343,"container":null},{"exe":"rcu_gp","pid":3,"consumption":0.0,"timestamp":1696347380.916241,"container":null},{"exe":"rcu_par_gp","pid":4,"consumption":0.0,"timestamp":1696347380.916248,"container":null},{"exe":"slub_flushwq","pid":5,"consumption":0.0,"timestamp":1696347380.9162555,"container":null},{"exe":"netns","pid":6,"consumption":0.0,"timestamp":1696347380.9162621,"container":null},{"exe":"kworker/0:0H-events_highpri","pid":8,"consumption":0.0,"timestamp":1696347380.916269,"container":null}],"sockets":[]},{"host":{"consumption":1349172.0,"timestamp":1696347381.9317214},"consumers":[{"exe":"scaphandre","pid":258028,"consumption":809503.0,"timestamp":1696347381.9417956,"container":null},{"exe":"ksoftirqd/3","pid":34,"consumption":269834.0,"timestamp":1696347381.93941,"container":null},{"exe":"kworker/1:1-events","pid":252649,"consumption":269834.0,"timestamp":1696347381.9414835,"container":null},{"exe":"amf","pid":257872,"consumption":269834.0,"timestamp":1696347381.9416802,"container":null},{"exe":"systemd","pid":1,"consumption":0.0,"timestamp":1696347381.9392254,"container":null},{"exe":"kthreadd","pid":2,"consumption":0.0,"timestamp":1696347381.9392338,"container":null},{"exe":"rcu_gp","pid":3,"consumption":0.0,"timestamp":1696347381.9392412,"container":null},{"exe":"rcu_par_gp","pid":4,"consumption":0.0,"timestamp":1696347381.9392478,"container":null},{"exe":"slub_flushwq","pid":5,"consumption":0.0,"timestamp":1696347381.9392545,"container":null},{"exe":"netns","pid":6,"consumption":0.0,"timestamp":1696347381.9392612,"container":null}],"sockets":[]},{"host":{"consumption":1515562.0,"timestamp":1696347382.9546344},"consumers":[{"exe":"scaphandre","pid":258028,"consumption":2273343.0,"timestamp":1696347382.9650395,"container":null},{"exe":"nrf","pid":257860,"consumption":757781.0,"timestamp":1696347382.9649103,"container":null},{"exe":"python3","pid":258003,"consumption":757781.0,"timestamp":1696347382.9650264,"container":null},{"exe":"systemd","pid":1,"consumption":0.0,"timestamp":1696347382.9624183,"container":null},{"exe":"kthreadd","pid":2,"consumption":0.0,"timestamp":1696347382.962427,"container":null},{"exe":"rcu_gp","pid":3,"consumption":0.0,"timestamp":1696347382.962434,"container":null},{"exe":"rcu_par_gp","pid":4,"consumption":0.0,"timestamp":1696347382.9624412,"container":null},{"exe":"slub_flushwq","pid":5,"consumption":0.0,"timestamp":1696347382.9624484,"container":null},{"exe":"netns","pid":6,"consumption":0.0,"timestamp":1696347382.962455,"container":null},{"exe":"kworker/0:0H-events_highpri","pid":8,"consumption":0.0,"timestamp":1696347382.9624622,"container":null}],"sockets":[]},{"host":{"consumption":1378890.0,"timestamp":1696347383.9779263},"consumers":[{"exe":"ksoftirqd/3","pid":34,"consumption":459630.0,"timestamp":1696347383.9854803,"container":null},{"exe":"update-notifier","pid":220909,"consumption":459630.0,"timestamp":1696347383.9874547,"container":null},{"exe":"scaphandre","pid":258028,"consumption":459630.0,"timestamp":1696347383.9878914,"container":null},{"exe":"systemd","pid":1,"consumption":0.0,"timestamp":1696347383.9852908,"container":null},{"exe":"kthreadd","pid":2,"consumption":0.0,"timestamp":1696347383.9852996,"container":null},{"exe":"rcu_gp","pid":3,"consumption":0.0,"timestamp":1696347383.9853067,"container":null},{"exe":"rcu_par_gp","pid":4,"consumption":0.0,"timestamp":1696347383.9853134,"container":null},{"exe":"slub_flushwq","pid":5,"consumption":0.0,"timestamp":1696347383.98532,"container":null},{"exe":"netns","pid":6,"consumption":0.0,"timestamp":1696347383.9853272,"container":null},{"exe":"kworker/0:0H-events_highpri","pid":8,"consumption":0.0,"timestamp":1696347383.9853349,"container":null}],"sockets":[]},{"host":{"consumption":1544422.0,"timestamp":1696347385.000852},"consumers":[{"exe":"scaphandre","pid":258028,"consumption":1029614.0,"timestamp":1696347385.011183,"container":null},{"exe":"mongod","pid":720,"consumption":514807.0,"timestamp":1696347385.0093637,"container":null},{"exe":"systemd","pid":1,"consumption":0.0,"timestamp":1696347385.0085557,"container":null},{"exe":"kthreadd","pid":2,"consumption":0.0,"timestamp":1696347385.0085645,"container":null},{"exe":"rcu_gp","pid":3,"consumption":0.0,"timestamp":1696347385.0085716,"container":null},{"exe":"rcu_par_gp","pid":4,"consumption":0.0,"timestamp":1696347385.0085795,"container":null},{"exe":"slub_flushwq","pid":5,"consumption":0.0,"timestamp":1696347385.008587,"container":null},{"exe":"netns","pid":6,"consumption":0.0,"timestamp":1696347385.0085938,"container":null},{"exe":"kworker/0:0H-events_highpri","pid":8,"consumption":0.0,"timestamp":1696347385.008601,"container":null},{"exe":"mm_percpu_wq","pid":10,"consumption":0.0,"timestamp":1696347385.0086083,"container":null}],"sockets":[]},{"host":{"consumption":1323842.0,"timestamp":1696347386.0242784},"consumers":[{"exe":"scaphandre","pid":258028,"consumption":1323842.0,"timestamp":1696347386.0339572,"container":null},{"exe":"ksoftirqd/3","pid":34,"consumption":441280.0,"timestamp":1696347386.0315945,"container":null},{"exe":"python3","pid":258003,"consumption":441280.0,"timestamp":1696347386.0339444,"container":null},{"exe":"systemd","pid":1,"consumption":0.0,"timestamp":1696347386.0314062,"container":null},{"exe":"kthreadd","pid":2,"consumption":0.0,"timestamp":1696347386.0314145,"container":null},{"exe":"rcu_gp","pid":3,"consumption":0.0,"timestamp":1696347386.0314212,"container":null},{"exe":"rcu_par_gp","pid":4,"consumption":0.0,"timestamp":1696347386.031428,"container":null},{"exe":"slub_flushwq","pid":5,"consumption":0.0,"timestamp":1696347386.0314345,"container":null},{"exe":"netns","pid":6,"consumption":0.0,"timestamp":1696347386.0314415,"container":null},{"exe":"kworker/0:0H-events_highpri","pid":8,"consumption":0.0,"timestamp":1696347386.0314486,"container":null}],"sockets":[]},{"host":{"consumption":1563706.0,"timestamp":1696347387.0469236},"consumers":[{"exe":"scaphandre","pid":258028,"consumption":938223.0,"timestamp":1696347387.0702035,"container":null},{"exe":"nrf","pid":257860,"consumption":625482.0,"timestamp":1696347387.0698845,"container":null},{"exe":"ksoftirqd/3","pid":34,"consumption":312741.0,"timestamp":1696347387.0649717,"container":null},{"exe":"mongod","pid":720,"consumption":312741.0,"timestamp":1696347387.0663123,"container":null},{"exe":"systemd","pid":1,"consumption":0.0,"timestamp":1696347387.0645304,"container":null},{"exe":"kthreadd","pid":2,"consumption":0.0,"timestamp":1696347387.0645497,"container":null},{"exe":"rcu_gp","pid":3,"consumption":0.0,"timestamp":1696347387.064567,"container":null},{"exe":"rcu_par_gp","pid":4,"consumption":0.0,"timestamp":1696347387.0645833,"container":null},{"exe":"slub_flushwq","pid":5,"consumption":0.0,"timestamp":1696347387.0645988,"container":null},{"exe":"netns","pid":6,"consumption":0.0,"timestamp":1696347387.0646145,"container":null}],"sockets":[]},{"host":{"consumption":1673681.0,"timestamp":1696347388.0936868},"consumers":[{"exe":"scaphandre","pid":258028,"consumption":760764.0,"timestamp":1696347388.1163614,"container":null},{"exe":"udr","pid":257893,"consumption":456458.0,"timestamp":1696347388.1162062,"container":null},{"exe":"ksoftirqd/3","pid":34,"consumption":304305.0,"timestamp":1696347388.1101892,"container":null},{"exe":"ausf","pid":257933,"consumption":304305.0,"timestamp":1696347388.1162968,"container":null},{"exe":"udm","pid":257915,"consumption":152152.0,"timestamp":1696347388.116251,"container":null},{"exe":"nssf","pid":257924,"consumption":152152.0,"timestamp":1696347388.116274,"container":null},{"exe":"systemd","pid":1,"consumption":0.0,"timestamp":1696347388.1096225,"container":null},{"exe":"kthreadd","pid":2,"consumption":0.0,"timestamp":1696347388.109649,"container":null},{"exe":"rcu_gp","pid":3,"consumption":0.0,"timestamp":1696347388.1096706,"container":null},{"exe":"rcu_par_gp","pid":4,"consumption":0.0,"timestamp":1696347388.1096914,"container":null}],"sockets":[]},{"host":{"consumption":1527233.0,"timestamp":1696347389.1413946},"consumers":[{"exe":"scaphandre","pid":258028,"consumption":1018155.0,"timestamp":1696347389.16343,"container":null},{"exe":"rcu_sched","pid":14,"consumption":254538.0,"timestamp":1696347389.1561327,"container":null},{"exe":"mongod","pid":720,"consumption":254538.0,"timestamp":1696347389.1585946,"container":null},{"exe":"python3","pid":258003,"consumption":254538.0,"timestamp":1696347389.1633885,"container":null},{"exe":"systemd","pid":1,"consumption":0.0,"timestamp":1696347389.1558197,"container":null},{"exe":"kthreadd","pid":2,"consumption":0.0,"timestamp":1696347389.1558428,"container":null},{"exe":"rcu_gp","pid":3,"consumption":0.0,"timestamp":1696347389.1558623,"container":null},{"exe":"rcu_par_gp","pid":4,"consumption":0.0,"timestamp":1696347389.1558967,"container":null},{"exe":"slub_flushwq","pid":5,"consumption":0.0,"timestamp":1696347389.155926,"container":null},{"exe":"netns","pid":6,"consumption":0.0,"timestamp":1696347389.1559548,"container":null}],"sockets":[]},{"host":{"consumption":1522943.0,"timestamp":1696347390.1886864},"consumers":[{"exe":"scaphandre","pid":258028,"consumption":1522943.0,"timestamp":1696347390.1991389,"container":null},{"exe":"mongod","pid":720,"consumption":761471.0,"timestamp":1696347390.1973147,"container":null},{"exe":"smf","pid":257883,"consumption":761471.0,"timestamp":1696347390.1990345,"container":null},{"exe":"ksoftirqd/3","pid":34,"consumption":380735.0,"timestamp":1696347390.196713,"container":null},{"exe":"thermald","pid":633,"consumption":380735.0,"timestamp":1696347390.1972446,"container":null},{"exe":"systemd","pid":1,"consumption":0.0,"timestamp":1696347390.1965206,"container":null},{"exe":"kthreadd","pid":2,"consumption":0.0,"timestamp":1696347390.1965299,"container":null},{"exe":"rcu_gp","pid":3,"consumption":0.0,"timestamp":1696347390.196537,"container":null},{"exe":"rcu_par_gp","pid":4,"consumption":0.0,"timestamp":1696347390.1965442,"container":null},{"exe":"slub_flushwq","pid":5,"consumption":0.0,"timestamp":1696347390.1965513,"container":null}],"sockets":[]},{"host":{"consumption":1541567.0,"timestamp":1696347391.212082},"consumers":[{"exe":"scaphandre","pid":258028,"consumption":1541567.0,"timestamp":1696347391.2220504,"container":null},{"exe":"ksoftirqd/3","pid":34,"consumption":513855.0,"timestamp":1696347391.2196684,"container":null},{"exe":"upf","pid":257838,"consumption":513855.0,"timestamp":1696347391.2219055,"container":null},{"exe":"systemd","pid":1,"consumption":0.0,"timestamp":1696347391.219482,"container":null},{"exe":"kthreadd","pid":2,"consumption":0.0,"timestamp":1696347391.2194912,"container":null},{"exe":"rcu_gp","pid":3,"consumption":0.0,"timestamp":1696347391.2194982,"container":null},{"exe":"rcu_par_gp","pid":4,"consumption":0.0,"timestamp":1696347391.219505,"container":null},{"exe":"slub_flushwq","pid":5,"consumption":0.0,"timestamp":1696347391.2195115,"container":null},{"exe":"netns","pid":6,"consumption":0.0,"timestamp":1696347391.2195182,"container":null},{"exe":"kworker/0:0H-events_highpri","pid":8,"consumption":0.0,"timestamp":1696347391.2195246,"container":null}],"sockets":[]},{"host":{"consumption":1577686.0,"timestamp":1696347392.235144},"consumers":[{"exe":"scaphandre","pid":258028,"consumption":1051790.0,"timestamp":1696347392.245802,"container":null},{"exe":"ksoftirqd/3","pid":34,"consumption":525895.0,"timestamp":1696347392.243399,"container":null},{"exe":"systemd-timesyn","pid":558,"consumption":525895.0,"timestamp":1696347392.2437568,"container":null},{"exe":"mongod","pid":720,"consumption":525895.0,"timestamp":1696347392.2440035,"container":null},{"exe":"systemd","pid":1,"consumption":0.0,"timestamp":1696347392.243211,"container":null},{"exe":"kthreadd","pid":2,"consumption":0.0,"timestamp":1696347392.24322,"container":null},{"exe":"rcu_gp","pid":3,"consumption":0.0,"timestamp":1696347392.2432275,"container":null},{"exe":"rcu_par_gp","pid":4,"consumption":0.0,"timestamp":1696347392.2432344,"container":null},{"exe":"slub_flushwq","pid":5,"consumption":0.0,"timestamp":1696347392.2432415,"container":null},{"exe":"netns","pid":6,"consumption":0.0,"timestamp":1696347392.243248,"container":null}],"sockets":[]},{"host":{"consumption":1515680.0,"timestamp":1696347393.2586617},"consumers":[{"exe":"scaphandre","pid":258028,"consumption":1010453.0,"timestamp":1696347393.269041,"container":null},{"exe":"ksoftirqd/3","pid":34,"consumption":505226.0,"timestamp":1696347393.2666323,"container":null},{"exe":"systemd","pid":1,"consumption":0.0,"timestamp":1696347393.2664402,"container":null},{"exe":"kthreadd","pid":2,"consumption":0.0,"timestamp":1696347393.2664492,"container":null},{"exe":"rcu_gp","pid":3,"consumption":0.0,"timestamp":1696347393.2664561,"container":null},{"exe":"rcu_par_gp","pid":4,"consumption":0.0,"timestamp":1696347393.2664638,"container":null},{"exe":"slub_flushwq","pid":5,"consumption":0.0,"timestamp":1696347393.266471,"container":null},{"exe":"netns","pid":6,"consumption":0.0,"timestamp":1696347393.2664776,"container":null},{"exe":"kworker/0:0H-events_highpri","pid":8,"consumption":0.0,"timestamp":1696347393.2664845,"container":null},{"exe":"mm_percpu_wq","pid":10,"consumption":0.0,"timestamp":1696347393.266491,"container":null}],"sockets":[]},{"host":{"consumption":1547361.0,"timestamp":1696347394.2817752},"consumers":[{"exe":"ksoftirqd/3","pid":34,"consumption":884206.0,"timestamp":1696347394.2896864,"container":null},{"exe":"amf","pid":257872,"consumption":884206.0,"timestamp":1696347394.292013,"container":null},{"exe":"scaphandre","pid":258028,"consumption":663154.0,"timestamp":1696347394.2921286,"container":null},{"exe":"python3","pid":258003,"consumption":221051.0,"timestamp":1696347394.292115,"container":null},{"exe":"systemd","pid":1,"consumption":0.0,"timestamp":1696347394.2894974,"container":null},{"exe":"kthreadd","pid":2,"consumption":0.0,"timestamp":1696347394.2895057,"container":null},{"exe":"rcu_gp","pid":3,"consumption":0.0,"timestamp":1696347394.2895124,"container":null},{"exe":"rcu_par_gp","pid":4,"consumption":0.0,"timestamp":1696347394.2895198,"container":null},{"exe":"slub_flushwq","pid":5,"consumption":0.0,"timestamp":1696347394.2895265,"container":null},{"exe":"netns","pid":6,"consumption":0.0,"timestamp":1696347394.289533,"container":null}],"sockets":[]},{"host":{"consumption":1503685.0,"timestamp":1696347395.3051784},"consumers":[{"exe":"scaphandre","pid":258028,"consumption":751842.0,"timestamp":1696347395.3149688,"container":null},{"exe":"ksoftirqd/3","pid":34,"consumption":375921.0,"timestamp":1696347395.3126106,"container":null},{"exe":"mongod","pid":720,"consumption":375921.0,"timestamp":1696347395.3131964,"container":null},{"exe":"amf","pid":257872,"consumption":375921.0,"timestamp":1696347395.3148525,"container":null},{"exe":"udr","pid":257893,"consumption":375921.0,"timestamp":1696347395.3148787,"container":null},{"exe":"systemd","pid":1,"consumption":0.0,"timestamp":1696347395.312427,"container":null},{"exe":"kthreadd","pid":2,"consumption":0.0,"timestamp":1696347395.3124354,"container":null},{"exe":"rcu_gp","pid":3,"consumption":0.0,"timestamp":1696347395.3124423,"container":null},{"exe":"rcu_par_gp","pid":4,"consumption":0.0,"timestamp":1696347395.3124492,"container":null},{"exe":"slub_flushwq","pid":5,"consumption":0.0,"timestamp":1696347395.3124564,"container":null}],"sockets":[]},{"host":{"consumption":1529830.0,"timestamp":1696347396.3278074},"consumers":[{"exe":"scaphandre","pid":258028,"consumption":1019886.0,"timestamp":1696347396.3383052,"container":null},{"exe":"ksoftirqd/3","pid":34,"consumption":509943.0,"timestamp":1696347396.3358667,"container":null},{"exe":"python3","pid":258003,"consumption":509943.0,"timestamp":1696347396.3382916,"container":null},{"exe":"systemd","pid":1,"consumption":0.0,"timestamp":1696347396.3356755,"container":null},{"exe":"kthreadd","pid":2,"consumption":0.0,"timestamp":1696347396.3356838,"container":null},{"exe":"rcu_gp","pid":3,"consumption":0.0,"timestamp":1696347396.335691,"container":null},{"exe":"rcu_par_gp","pid":4,"consumption":0.0,"timestamp":1696347396.335698,"container":null},{"exe":"slub_flushwq","pid":5,"consumption":0.0,"timestamp":1696347396.3357048,"container":null},{"exe":"netns","pid":6,"consumption":0.0,"timestamp":1696347396.3357115,"container":null},{"exe":"kworker/0:0H-events_highpri","pid":8,"consumption":0.0,"timestamp":1696347396.335719,"container":null}],"sockets":[]},{"host":{"consumption":1539472.0,"timestamp":1696347397.351049},"consumers":[{"exe":"scaphandre","pid":258028,"consumption":1539472.0,"timestamp":1696347397.3608272,"container":null},{"exe":"mongod","pid":720,"consumption":1026314.0,"timestamp":1696347397.359028,"container":null},{"exe":"ksoftirqd/3","pid":34,"consumption":513157.0,"timestamp":1696347397.3584414,"container":null},{"exe":"nrf","pid":257860,"consumption":513157.0,"timestamp":1696347397.360698,"container":null},{"exe":"systemd","pid":1,"consumption":0.0,"timestamp":1696347397.3582559,"container":null},{"exe":"kthreadd","pid":2,"consumption":0.0,"timestamp":1696347397.3582642,"container":null},{"exe":"rcu_gp","pid":3,"consumption":0.0,"timestamp":1696347397.3582711,"container":null},{"exe":"rcu_par_gp","pid":4,"consumption":0.0,"timestamp":1696347397.3582778,"container":null},{"exe":"slub_flushwq","pid":5,"consumption":0.0,"timestamp":1696347397.3582842,"container":null},{"exe":"netns","pid":6,"consumption":0.0,"timestamp":1696347397.3582911,"container":null}],"sockets":[]},{"host":{"consumption":1569667.0,"timestamp":1696347398.3738935},"consumers":[{"exe":"ksoftirqd/3","pid":34,"consumption":392416.0,"timestamp":1696347398.3817756,"container":null},{"exe":"scaphandre","pid":258028,"consumption":392416.0,"timestamp":1696347398.3842156,"container":null},{"exe":"systemd","pid":1,"consumption":0.0,"timestamp":1696347398.3815854,"container":null},{"exe":"kthreadd","pid":2,"consumption":0.0,"timestamp":1696347398.3815942,"container":null},{"exe":"rcu_gp","pid":3,"consumption":0.0,"timestamp":1696347398.3816016,"container":null},{"exe":"rcu_par_gp","pid":4,"consumption":0.0,"timestamp":1696347398.3816085,"container":null},{"exe":"slub_flushwq","pid":5,"consumption":0.0,"timestamp":1696347398.3816156,"container":null},{"exe":"netns","pid":6,"consumption":0.0,"timestamp":1696347398.381622,"container":null},{"exe":"kworker/0:0H-events_highpri","pid":8,"consumption":0.0,"timestamp":1696347398.381629,"container":null},{"exe":"mm_percpu_wq","pid":10,"consumption":0.0,"timestamp":1696347398.3816357,"container":null}],"sockets":[]}]